{"cameraMode":{"drawMode":0,"name":"Shaded","section":"Shading Mode"},"sceneLighting":false,"audioPlay":false,"sceneViewState":{"m_AlwaysRefresh":false,"showFog":true,"showSkybox":false,"showFlares":true,"showImageEffects":true,"showParticleSystems":true,"showVisualEffectGraphs":true,"m_FxEnabled":true},"in2DMode":false,"pivot":{"x":-4.866151332855225,"y":3.7539501190185549,"z":21.77417755126953},"rotation":{"x":-0.8611687421798706,"y":0.10995560884475708,"z":0.2107422947883606,"w":0.44931769371032717},"size":8.97247314453125,"orthographic":false}